ai_function/__init__.py
ai_function/ai_function.py
ai_function_library-0.1.0.dist-info/LICENSE
ai_function_library-0.1.0.dist-info/METADATA
ai_function_library-0.1.0.dist-info/WHEEL
ai_function_library-0.1.0.dist-info/top_level.txt
ai_function_library-0.1.0.dist-info/RECORD
