Metadata-Version: 2.1
Name: ai-function-library
Version: 0.1.0
Summary: A Python library for converting functions into their source code strings
Home-page: UNKNOWN
Author: rafboard
Author-email: rlopezmanas@gmail.com
License: UNKNOWN
Platform: UNKNOWN
